LICENSE
MANIFEST.in
README.md
setup.cfg
setup.py
tcp_reader/__init__.py
tcp_reader.egg-info/PKG-INFO
tcp_reader.egg-info/SOURCES.txt
tcp_reader.egg-info/dependency_links.txt
tcp_reader.egg-info/requires.txt
tcp_reader.egg-info/top_level.txt