Metadata-Version: 2.1
Name: tcp-reader
Version: 0.1.0.post1
Summary: TCP Stream Reader
Home-page: https://git.brn.li/SWW13/tcp-reader-py
Author: Simon Wörner
Author-email: git@simon-woerner.de
License: MIT
Platform: UNKNOWN
Classifier: Programming Language :: Python :: 3
Classifier: License :: OSI Approved :: MIT License
Classifier: Operating System :: OS Independent
